base114514.py
base114514-0.4.dist-info/LICENSE
base114514-0.4.dist-info/METADATA
base114514-0.4.dist-info/WHEEL
base114514-0.4.dist-info/entry_points.txt
base114514-0.4.dist-info/top_level.txt
base114514-0.4.dist-info/RECORD
