Metadata-Version: 2.1
Name: base114514
Version: 0.4
Summary: Base114514 encoding, the algorithm from Shimokitazawa
Home-page: https://github.com/YidaozhanYa/base114514
Author: Yidaozhan Ya
Author-email: ydz@yidaozhan.top
Maintainer: Yidaozhan Ya
Maintainer-email: ydz@yidaozhan.top
Keywords: base114514,base64
Classifier: Programming Language :: Python :: 3
Classifier: Operating System :: OS Independent
Requires-Python: >=3.10
License-File: LICENSE
